piptools_sync/__init__.py
piptools_sync/config.toml
piptools_sync/mapping.json
piptools_sync/piptools_sync.py
piptools_sync-1.0.4.dist-info/LICENSE
piptools_sync-1.0.4.dist-info/METADATA
piptools_sync-1.0.4.dist-info/PKG-INFO.rum-bak
piptools_sync-1.0.4.dist-info/WHEEL
piptools_sync-1.0.4.dist-info/entry_points.txt
piptools_sync-1.0.4.dist-info/top_level.txt
piptools_sync-1.0.4.dist-info/RECORD
