Metadata-Version: 2.1
Name: piptools-sync
Version: 1.0.4
Summary: A piptools pre-commit version sync utility
Home-page: https://github.com/Stephen-RA-King/piptools-sync
Download-URL: https://github.com/Stephen-RA-King/piptools_sync/archive/refs/heads/main.zip
Author: Stephen R A King
Author-email: sking.github@gmail.com
Maintainer: Stephen R A King
Maintainer-email: sking.github@gmail.com
License: MIT
Project-URL: documentation, https://piptools-sync.readthedocs.io/en/latest/
Project-URL: Release Notes, https://github.com/Stephen-RA-King/piptools_sync/releases
Project-URL: Source Code, https://github.com/Stephen-RA-King/piptools_sync/
Project-URL: Issue Tracker, https://github.com/Stephen-RA-King/piptools_sync/issues
Keywords: pre-commit-hooks,version-sync,pip-tools,pre-commit,dependency-manager
Platform: Any
Classifier: Development Status :: 5 - Production/Stable
Classifier: Environment :: Console
Classifier: Intended Audience :: Developers
Classifier: License :: OSI Approved :: MIT License
Classifier: Operating System :: OS Independent
Classifier: Natural Language :: English
Classifier: Programming Language :: Python :: 3
Classifier: Programming Language :: Python :: 3 :: Only
Classifier: Programming Language :: Python :: 3.9
Classifier: Programming Language :: Python :: 3.10
Classifier: Programming Language :: Python :: 3.11
Requires-Python: >=3.8
License-File: LICENSE
Requires-Dist: aiohttp (>=3.8.4)
Requires-Dist: click (>=8.1.3)
Requires-Dist: gitpython (>=3.1.31)
Requires-Dist: pyyaml (>=6.0)
Requires-Dist: requests (>=2.28.2)
Requires-Dist: toml (>=0.10.2)
Requires-Dist: tqdm (>=4.64.1)
